{
  "hit_by_label": {
    "QAOA-3reg_q7_d6": 10,
    "QFT-Like_q13_d6": 5,
    "QAOA-3reg_q15_d4": 5,
    "QSIM-XXZ_q15_d4": 6,
    "VQE-Full_q5_d4": 5,
    "GHZ-Chain_q17_d6": 8,
    "QAOA-3reg_q17_d4": 5,
    "GHZ-Chain_q11_d4": 2,
    "GHZ-Chain_q5_d6": 5,
    "QAOA-3reg_q5_d2": 3,
    "LinearEnt_q7_d6": 6,
    "RCA_q11_d4": 3,
    "QSIM-XXZ_q11_d6": 1,
    "GHZ-Chain_q5_d2": 4,
    "GHZ-Chain_q15_d2": 7,
    "VQE-Full_q13_d4": 2,
    "VQE-Full_q13_d6": 3,
    "RCA_q15_d4": 4,
    "GHZ-Chain_q7_d6": 3,
    "LinearEnt_q11_d4": 7,
    "VQE-Full_q5_d6": 1,
    "LinearEnt_q13_d2": 2,
    "GHZ-Chain_q13_d6": 3,
    "RCA_q7_d4": 4,
    "RCA_q13_d2": 4,
    "QAOA-3reg_q17_d2": 4,
    "VQE-Full_q7_d2": 1,
    "RCA_q11_d6": 5,
    "GHZ-Chain_q17_d2": 3,
    "QSIM-XXZ_q13_d4": 2,
    "QAOA-3reg_q17_d6": 1,
    "QFT-Like_q7_d4": 1,
    "QSIM-XXZ_q7_d4": 3,
    "QFT-Like_q17_d4": 1,
    "VQE-Full_q17_d4": 1,
    "QSIM-XXZ_q5_d2": 1,
    "GHZ-Chain_q13_d2": 1
  },
  "total_hits": 132,
  "cache_size_series": [
    {
      "t": 0.0,
      "size": 4
    },
    {
      "t": 0.03384809987619519,
      "size": 4
    },
    {
      "t": 0.03384809987619519,
      "size": 4
    },
    {
      "t": 0.03384809987619519,
      "size": 4
    },
    {
      "t": 0.03384809987619519,
      "size": 4
    },
    {
      "t": 0.03384809987619519,
      "size": 6
    },
    {
      "t": 0.07206799974665046,
      "size": 7
    },
    {
      "t": 0.10975780012086034,
      "size": 8
    },
    {
      "t": 0.1471911002881825,
      "size": 9
    },
    {
      "t": 0.24153730040416121,
      "size": 9
    },
    {
      "t": 0.24153730040416121,
      "size": 10
    },
    {
      "t": 0.27448780043050647,
      "size": 11
    },
    {
      "t": 0.3019639002159238,
      "size": 11
    },
    {
      "t": 0.3019639002159238,
      "size": 12
    },
    {
      "t": 0.6163455001078546,
      "size": 13
    },
    {
      "t": 0.6621591001749039,
      "size": 14
    },
    {
      "t": 0.6898411000147462,
      "size": 15
    },
    {
      "t": 0.7232834002934396,
      "size": 15
    },
    {
      "t": 0.7232834002934396,
      "size": 16
    },
    {
      "t": 0.7797296005301178,
      "size": 17
    },
    {
      "t": 0.8077584002166986,
      "size": 17
    },
    {
      "t": 0.8077584002166986,
      "size": 17
    },
    {
      "t": 0.8077584002166986,
      "size": 18
    },
    {
      "t": 0.8540923004038632,
      "size": 19
    },
    {
      "t": 0.9122917004860938,
      "size": 20
    },
    {
      "t": 0.9389793002046645,
      "size": 21
    },
    {
      "t": 0.9799593002535403,
      "size": 22
    },
    {
      "t": 1.0197577001526952,
      "size": 23
    },
    {
      "t": 1.1310684001073241,
      "size": 24
    },
    {
      "t": 1.1987922000698745,
      "size": 25
    },
    {
      "t": 1.2285192999988794,
      "size": 25
    },
    {
      "t": 1.2285192999988794,
      "size": 25
    },
    {
      "t": 1.2285192999988794,
      "size": 26
    },
    {
      "t": 1.3667712998576462,
      "size": 27
    },
    {
      "t": 1.440546099562198,
      "size": 28
    },
    {
      "t": 1.57507579959929,
      "size": 28
    },
    {
      "t": 1.57507579959929,
      "size": 28
    },
    {
      "t": 1.57507579959929,
      "size": 28
    },
    {
      "t": 1.57507579959929,
      "size": 29
    },
    {
      "t": 1.6128473994322121,
      "size": 29
    },
    {
      "t": 1.6128473994322121,
      "size": 29
    },
    {
      "t": 1.6128473994322121,
      "size": 30
    },
    {
      "t": 1.6381470994092524,
      "size": 31
    },
    {
      "t": 1.6734819994308054,
      "size": 31
    },
    {
      "t": 1.6734819994308054,
      "size": 31
    },
    {
      "t": 1.6734819994308054,
      "size": 31
    },
    {
      "t": 1.6734819994308054,
      "size": 31
    },
    {
      "t": 1.6734819994308054,
      "size": 31
    },
    {
      "t": 1.6734819994308054,
      "size": 31
    },
    {
      "t": 1.6734819994308054,
      "size": 31
    },
    {
      "t": 1.6734819994308054,
      "size": 31
    },
    {
      "t": 1.6734819994308054,
      "size": 32
    },
    {
      "t": 1.7168066990561783,
      "size": 32
    },
    {
      "t": 1.7168066990561783,
      "size": 33
    },
    {
      "t": 1.7593878991901875,
      "size": 34
    },
    {
      "t": 1.7850993992760777,
      "size": 34
    },
    {
      "t": 1.7850993992760777,
      "size": 34
    },
    {
      "t": 1.7850993992760777,
      "size": 35
    },
    {
      "t": 1.8439375991001725,
      "size": 35
    },
    {
      "t": 1.8439375991001725,
      "size": 36
    },
    {
      "t": 1.8808786990121007,
      "size": 36
    },
    {
      "t": 1.8808786990121007,
      "size": 36
    },
    {
      "t": 1.8808786990121007,
      "size": 36
    },
    {
      "t": 1.8808786990121007,
      "size": 36
    },
    {
      "t": 1.8808786990121007,
      "size": 36
    },
    {
      "t": 1.8808786990121007,
      "size": 36
    },
    {
      "t": 1.8808786990121007,
      "size": 36
    },
    {
      "t": 1.8808786990121007,
      "size": 37
    },
    {
      "t": 1.9253852991387248,
      "size": 38
    },
    {
      "t": 1.958654299378395,
      "size": 38
    },
    {
      "t": 1.958654299378395,
      "size": 38
    },
    {
      "t": 1.958654299378395,
      "size": 38
    },
    {
      "t": 1.958654299378395,
      "size": 38
    },
    {
      "t": 1.958654299378395,
      "size": 38
    },
    {
      "t": 1.958654299378395,
      "size": 38
    },
    {
      "t": 1.958654299378395,
      "size": 38
    },
    {
      "t": 1.958654299378395,
      "size": 38
    },
    {
      "t": 1.958654299378395,
      "size": 38
    },
    {
      "t": 1.958654299378395,
      "size": 38
    },
    {
      "t": 1.958654299378395,
      "size": 38
    },
    {
      "t": 1.958654299378395,
      "size": 39
    },
    {
      "t": 2.000668699387461,
      "size": 39
    },
    {
      "t": 2.000668699387461,
      "size": 39
    },
    {
      "t": 2.000668699387461,
      "size": 39
    },
    {
      "t": 2.000668699387461,
      "size": 40
    },
    {
      "t": 2.24233749974519,
      "size": 40
    },
    {
      "t": 2.24233749974519,
      "size": 41
    },
    {
      "t": 2.2706723995506763,
      "size": 42
    },
    {
      "t": 2.302843699697405,
      "size": 42
    },
    {
      "t": 2.302843699697405,
      "size": 43
    },
    {
      "t": 2.6378940995782614,
      "size": 43
    },
    {
      "t": 2.6378940995782614,
      "size": 43
    },
    {
      "t": 2.6378940995782614,
      "size": 43
    },
    {
      "t": 2.6378940995782614,
      "size": 44
    },
    {
      "t": 2.669194399844855,
      "size": 44
    },
    {
      "t": 2.669194399844855,
      "size": 44
    },
    {
      "t": 2.669194399844855,
      "size": 45
    },
    {
      "t": 2.7034212998114526,
      "size": 45
    },
    {
      "t": 2.7034212998114526,
      "size": 45
    },
    {
      "t": 2.7034212998114526,
      "size": 45
    },
    {
      "t": 2.7034212998114526,
      "size": 45
    },
    {
      "t": 2.7034212998114526,
      "size": 45
    },
    {
      "t": 2.7034212998114526,
      "size": 45
    },
    {
      "t": 2.7034212998114526,
      "size": 45
    },
    {
      "t": 2.7034212998114526,
      "size": 45
    },
    {
      "t": 2.7034212998114526,
      "size": 46
    },
    {
      "t": 2.7503720996901393,
      "size": 47
    },
    {
      "t": 3.186279199551791,
      "size": 48
    },
    {
      "t": 3.2478577992878854,
      "size": 48
    },
    {
      "t": 3.2478577992878854,
      "size": 48
    },
    {
      "t": 3.2478577992878854,
      "size": 48
    },
    {
      "t": 3.2478577992878854,
      "size": 48
    },
    {
      "t": 3.2478577992878854,
      "size": 49
    },
    {
      "t": 3.300749299582094,
      "size": 50
    },
    {
      "t": 3.3730436991900206,
      "size": 50
    },
    {
      "t": 3.3730436991900206,
      "size": 50
    },
    {
      "t": 3.3730436991900206,
      "size": 50
    },
    {
      "t": 3.3730436991900206,
      "size": 50
    },
    {
      "t": 3.3730436991900206,
      "size": 51
    },
    {
      "t": 3.4532374991104007,
      "size": 52
    },
    {
      "t": 3.5190042993053794,
      "size": 52
    },
    {
      "t": 3.5190042993053794,
      "size": 52
    },
    {
      "t": 3.5190042993053794,
      "size": 52
    },
    {
      "t": 3.5190042993053794,
      "size": 52
    },
    {
      "t": 3.5190042993053794,
      "size": 52
    },
    {
      "t": 3.5190042993053794,
      "size": 52
    },
    {
      "t": 3.5190042993053794,
      "size": 52
    },
    {
      "t": 3.5190042993053794,
      "size": 52
    },
    {
      "t": 3.5190042993053794,
      "size": 53
    },
    {
      "t": 3.5510904993861914,
      "size": 53
    },
    {
      "t": 3.5510904993861914,
      "size": 53
    },
    {
      "t": 3.5510904993861914,
      "size": 54
    },
    {
      "t": 3.6038235994055867,
      "size": 54
    },
    {
      "t": 3.6038235994055867,
      "size": 54
    },
    {
      "t": 3.6038235994055867,
      "size": 55
    },
    {
      "t": 3.6394082992337644,
      "size": 56
    },
    {
      "t": 3.6906404988840222,
      "size": 57
    },
    {
      "t": 3.734910098835826,
      "size": 57
    },
    {
      "t": 3.734910098835826,
      "size": 57
    },
    {
      "t": 3.734910098835826,
      "size": 57
    },
    {
      "t": 3.734910098835826,
      "size": 58
    },
    {
      "t": 3.770768098998815,
      "size": 59
    },
    {
      "t": 3.8280229992233217,
      "size": 59
    },
    {
      "t": 3.8280229992233217,
      "size": 60
    },
    {
      "t": 3.904260898940265,
      "size": 60
    },
    {
      "t": 3.904260898940265,
      "size": 61
    },
    {
      "t": 3.9533799989148974,
      "size": 61
    },
    {
      "t": 3.9533799989148974,
      "size": 61
    },
    {
      "t": 3.9533799989148974,
      "size": 61
    },
    {
      "t": 3.9533799989148974,
      "size": 62
    },
    {
      "t": 3.9823805992491543,
      "size": 62
    },
    {
      "t": 3.9823805992491543,
      "size": 62
    },
    {
      "t": 3.9823805992491543,
      "size": 63
    },
    {
      "t": 4.019270199351013,
      "size": 63
    },
    {
      "t": 4.019270199351013,
      "size": 63
    },
    {
      "t": 4.019270199351013,
      "size": 63
    },
    {
      "t": 4.019270199351013,
      "size": 63
    },
    {
      "t": 4.019270199351013,
      "size": 63
    },
    {
      "t": 4.019270199351013,
      "size": 63
    },
    {
      "t": 4.019270199351013,
      "size": 63
    },
    {
      "t": 4.019270199351013,
      "size": 63
    },
    {
      "t": 4.019270199351013,
      "size": 63
    },
    {
      "t": 4.019270199351013,
      "size": 64
    },
    {
      "t": 4.06398189952597,
      "size": 64
    },
    {
      "t": 4.06398189952597,
      "size": 64
    },
    {
      "t": 4.06398189952597,
      "size": 64
    },
    {
      "t": 4.06398189952597,
      "size": 64
    },
    {
      "t": 4.06398189952597,
      "size": 65
    },
    {
      "t": 4.096665899734944,
      "size": 66
    },
    {
      "t": 4.147842499893159,
      "size": 66
    },
    {
      "t": 4.147842499893159,
      "size": 66
    },
    {
      "t": 4.147842499893159,
      "size": 66
    },
    {
      "t": 4.147842499893159,
      "size": 66
    },
    {
      "t": 4.147842499893159,
      "size": 66
    },
    {
      "t": 4.147842499893159,
      "size": 66
    },
    {
      "t": 4.147842499893159,
      "size": 66
    },
    {
      "t": 4.147842499893159,
      "size": 66
    },
    {
      "t": 4.147842499893159,
      "size": 66
    },
    {
      "t": 4.147842499893159,
      "size": 66
    },
    {
      "t": 4.147842499893159,
      "size": 66
    },
    {
      "t": 4.147842499893159,
      "size": 66
    },
    {
      "t": 4.147842499893159,
      "size": 67
    },
    {
      "t": 4.2185672000050545,
      "size": 67
    },
    {
      "t": 4.2185672000050545,
      "size": 67
    },
    {
      "t": 4.2185672000050545,
      "size": 68
    },
    {
      "t": 4.2462895000353456,
      "size": 68
    },
    {
      "t": 4.2462895000353456,
      "size": 68
    },
    {
      "t": 4.2462895000353456,
      "size": 69
    },
    {
      "t": 4.352148000150919,
      "size": 70
    },
    {
      "t": 4.3836191999726,
      "size": 70
    },
    {
      "t": 4.3836191999726,
      "size": 71
    },
    {
      "t": 4.412190200295299,
      "size": 71
    },
    {
      "t": 4.412190200295299,
      "size": 71
    },
    {
      "t": 4.412190200295299,
      "size": 71
    },
    {
      "t": 4.412190200295299,
      "size": 72
    },
    {
      "t": 4.463276400230825,
      "size": 72
    },
    {
      "t": 4.463276400230825,
      "size": 72
    },
    {
      "t": 4.463276400230825,
      "size": 72
    },
    {
      "t": 4.463276400230825,
      "size": 72
    },
    {
      "t": 4.463276400230825,
      "size": 72
    }
  ]
}